wavespeed_mcp/__init__.py
wavespeed_mcp/__main__.py
wavespeed_mcp/client.py
wavespeed_mcp/const.py
wavespeed_mcp/exceptions.py
wavespeed_mcp/server.py
wavespeed_mcp/utils.py
wavespeed_mcp-0.1.27.dist-info/METADATA
wavespeed_mcp-0.1.27.dist-info/WHEEL
wavespeed_mcp-0.1.27.dist-info/entry_points.txt
wavespeed_mcp-0.1.27.dist-info/top_level.txt
wavespeed_mcp-0.1.27.dist-info/RECORD
