Metadata-Version: 2.4
Name: wavespeed-mcp
Version: 0.1.27
Summary: WaveSpeed MCP Server
Author-email: Wavespeed AI Team <support@wavespeed.ai>
Keywords: wavespeed,mcp,image-generation,video-generation
Classifier: Development Status :: 4 - Beta
Classifier: Intended Audience :: Developers
Classifier: License :: OSI Approved :: MIT License
Classifier: Programming Language :: Python :: 3
Classifier: Programming Language :: Python :: 3.11
Classifier: Programming Language :: Python :: 3.12
Requires-Python: >=3.11
Requires-Dist: mcp[cli]>=1.6.0
Requires-Dist: fastapi==0.109.2
Requires-Dist: uvicorn==0.27.1
Requires-Dist: python-dotenv==1.0.1
Requires-Dist: pydantic>=2.6.1
Requires-Dist: httpx==0.28.1
Requires-Dist: requests==2.31.0
Requires-Dist: tqdm>=4.66.0
Requires-Dist: setuptools>=80.9.0
Provides-Extra: dev
Requires-Dist: pre-commit==3.6.2; extra == "dev"
Requires-Dist: ruff==0.3.0; extra == "dev"
Requires-Dist: fastmcp==0.4.1; extra == "dev"
Requires-Dist: pytest==8.0.0; extra == "dev"
Requires-Dist: pytest-cov==4.1.0; extra == "dev"
Requires-Dist: twine==6.1.0; extra == "dev"
Requires-Dist: build>=1.0.3; extra == "dev"
